bgenv/__init__.py
bgenv-0.1.0.dist-info/WHEEL
bgenv-0.1.0.dist-info/METADATA
bgenv-0.1.0.dist-info/RECORD
